{"chunk_definitions":[{"row":50,"row_count":1,"visible":true,"expansion_state":0,"options":{"engine":"r","eval":false,"label":"unnamed-chunk-2","dev":"png"},"document_id":"9DFF02FB","chunk_id":"cz2gkh2zjv6yw","chunk_label":"unnamed-chunk-1"},{"row":127,"row_count":1,"visible":true,"expansion_state":0,"options":{"engine":"r","class.source":"fold-hide","label":"unnamed-chunk-3","dev":"png"},"document_id":"9DFF02FB","chunk_id":"cm8g9jxjm69jt","chunk_label":"unnamed-chunk-2"},{"row":165,"row_count":1,"visible":true,"expansion_state":0,"options":{"engine":"r","class.source":"fold-hide","label":"unnamed-chunk-4","dev":"png"},"document_id":"9DFF02FB","chunk_id":"chq48jk6lvle0","chunk_label":"unnamed-chunk-3"},{"row":214,"row_count":1,"visible":true,"expansion_state":0,"options":{"engine":"r","class.source":"fold-hide","label":"unnamed-chunk-5","dev":"png"},"document_id":"9DFF02FB","chunk_id":"c8zgx4ckzhb3l","chunk_label":"unnamed-chunk-4"},{"row":504,"row_count":1,"visible":true,"expansion_state":0,"options":{"engine":"r","class.source":"fold-hide","label":"unnamed-chunk-13","dev":"png"},"document_id":"9DFF02FB","chunk_id":"cl4319csjp417","chunk_label":"unnamed-chunk-5"},{"row":611,"row_count":1,"visible":true,"expansion_state":0,"options":{"engine":"r","label":"unnamed-chunk-8","dev":"png"},"document_id":"9DFF02FB","chunk_id":"c5tlhc51uo5iq","chunk_label":"unnamed-chunk-6"},{"row":723,"row_count":1,"visible":true,"expansion_state":0,"options":{"engine":"r","class.source":"fold-hide","label":"unnamed-chunk-27","dev":"png"},"document_id":"9DFF02FB","chunk_id":"cw66dfv3n353a","chunk_label":"unnamed-chunk-9"},{"row":776,"row_count":1,"visible":true,"expansion_state":0,"options":{"engine":"r","class.source":"fold-hide","label":"unnamed-chunk-28","dev":"png"},"document_id":"9DFF02FB","chunk_id":"cbxnuyusipje7","chunk_label":"unnamed-chunk-10"},{"row":812,"row_count":1,"visible":true,"expansion_state":0,"options":{"engine":"r","class.source":"fold-hide","label":"unnamed-chunk-29","dev":"png"},"document_id":"9DFF02FB","chunk_id":"cj865yosyq3sw","chunk_label":"unnamed-chunk-11"}],"doc_write_time":1717249431}